mlforge/__init__.py
mlforge/__main__.py
mlforge/cli.py
mlforge/core.py
mlforge/entities.py
mlforge/errors.py
mlforge/loader.py
mlforge/logging.py
mlforge/manifest.py
mlforge/metrics.py
mlforge/online.py
mlforge/profiles.py
mlforge/py.typed
mlforge/results.py
mlforge/retrieval.py
mlforge/serve.py
mlforge/store.py
mlforge/timestamps.py
mlforge/types.py
mlforge/utils.py
mlforge/validation.py
mlforge/validators.py
mlforge/version.py
mlforge/compilers/__init__.py
mlforge/compilers/base.py
mlforge/compilers/duckdb.py
mlforge/compilers/polars.py
mlforge/engines/__init__.py
mlforge/engines/base.py
mlforge/engines/duckdb.py
mlforge/engines/polars.py
mlforge/integrations/__init__.py
mlforge/integrations/mlflow.py
mlforge/sources/__init__.py
mlforge/sources/base.py
mlforge/sources/formats.py
mlforge_sdk-0.7.0.dist-info/METADATA
mlforge_sdk-0.7.0.dist-info/WHEEL
mlforge_sdk-0.7.0.dist-info/entry_points.txt
mlforge_sdk-0.7.0.dist-info/licenses/LICENSE
mlforge_sdk-0.7.0.dist-info/RECORD
