Metadata-Version: 2.4
Name: mlforge-sdk
Version: 0.7.0
Summary: ML Platform for your local machine using cheap cloud services for scalable resources.
Project-URL: Homepage, https://github.com/chonalchendo/mlforge
Project-URL: Documentation, https://chonalchendo.github.io/mlforge
Project-URL: Repository, https://github.com/chonalchendo/mlforge
Author-email: chonalchendo <110059232+chonalchendo@users.noreply.github.com>
License-File: LICENSE
Keywords: feature-store,machine-learning,mlops,polars
Classifier: Development Status :: 3 - Alpha
Classifier: Intended Audience :: Developers
Classifier: License :: OSI Approved :: MIT License
Classifier: Programming Language :: Python :: 3.13
Requires-Python: >=3.13.0
Requires-Dist: cyclopts>=4.2.1
Requires-Dist: fastapi>=0.115.0
Requires-Dist: hatchling>=1.28.0
Requires-Dist: loguru>=0.7.3
Requires-Dist: omegaconf>=2.3.0
Requires-Dist: polars>=1.35.2
Requires-Dist: prometheus-client>=0.21.0
Requires-Dist: pyarrow>=22.0.0
Requires-Dist: pydantic>=2.12.4
Requires-Dist: s3fs>=2025.12.0
Requires-Dist: setuptools>=80.9.0
Requires-Dist: uvicorn>=0.34.0
Provides-Extra: all
Requires-Dist: duckdb>=1.4.3; extra == 'all'
Requires-Dist: gcsfs>=2025.12.0; extra == 'all'
Requires-Dist: mlflow>=2.0.0; extra == 'all'
Requires-Dist: redis>=7.1.0; extra == 'all'
Provides-Extra: duckdb
Requires-Dist: duckdb>=1.4.3; extra == 'duckdb'
Provides-Extra: dynamodb
Requires-Dist: boto3>=1.28.0; extra == 'dynamodb'
Provides-Extra: gcs
Requires-Dist: gcsfs>=2025.12.0; extra == 'gcs'
Provides-Extra: mlflow
Requires-Dist: mlflow>=2.0.0; extra == 'mlflow'
Provides-Extra: redis
Requires-Dist: redis>=7.1.0; extra == 'redis'
